pi3/__init__.py
pi3/smart_workspace.py
pi3_smart_workspace-0.1.21.data/scripts/smart_workspace.py
pi3_smart_workspace-0.1.21.dist-info/LICENSE
pi3_smart_workspace-0.1.21.dist-info/METADATA
pi3_smart_workspace-0.1.21.dist-info/WHEEL
pi3_smart_workspace-0.1.21.dist-info/entry_points.txt
pi3_smart_workspace-0.1.21.dist-info/top_level.txt
pi3_smart_workspace-0.1.21.dist-info/RECORD
