Metadata-Version: 2.1
Name: pi3-smart-workspace
Version: 0.1.21
Summary: Simple program that looks through the i3 config and finds the bound workspaces for each output, and then opening that workspace on the output, that the mouse is currently on.
Home-page: https://github.com/GeneralDenmark/PyOutputHandler
Author: Asger Geel Weirsøe
Author-email: asger@weirsoe.dk
License: Apache-2.0 License 
Platform: UNKNOWN
Classifier: Development Status :: 3 - Alpha
Classifier: License :: OSI Approved :: Apache Software License
Classifier: Operating System :: POSIX :: Linux
Classifier: Programming Language :: Python :: 3
Classifier: Topic :: Desktop Environment :: Window Managers
Requires-Dist: evdev (==1.3.0)
Requires-Dist: i3ipc (==2.2.1)
Requires-Dist: pynput (==1.7.1)
Requires-Dist: python-xlib (==0.27)
Requires-Dist: six (==1.15.0)
